vitu/__init__.py
vitu/ai.py
vitu/configuration.py
vitu/account/account.py
vitu/account/account_manager.py
vitu/account/contract_account.py
vitu/account/spot_account.py
vitu/context/clock.py
vitu/context/context.py
vitu/core/match_engine.py
vitu/data/cache.py
vitu/data/data.py
vitu/data/static/min_order.py
vitu/report/complete_report.py
vitu/report/report.py
vitu/report/simple_report.py
vitu/strategy/strategy.py
vitu/trade/order/order.py
vitu/trade/order/trade.py
vitu/trade/portfoilo/portfolio.py
vitu/trade/position/contract_position.py
vitu/trade/position/portfolio_position.py
vitu/trade/position/position.py
vitu/trade/position/spot_position.py
vitu/universe/universe.py
vitu/utils/__init__.py
vitu/utils/data_utils.py
vitu/utils/date_utils.py
vitu/utils/error_utils.py
vitu/utils/log_utils.py
vitu/utils/min_qty.py
vitu/utils/output_utils.py
vitu/utils/trade_utils.py
vitu-2.1.0.data/data/vitu/wqy-microhei.ttc
vitudata/__init__.py
vitudata/config.py
vitudata/exceptions.py
vitudata/apis/__init__.py
vitudata/apis/data.py
vitudata/apis/data_utils.py
vitu-2.1.0.dist-info/AUTHORS.txt
vitu-2.1.0.dist-info/LICENSE.txt
vitu-2.1.0.dist-info/METADATA
vitu-2.1.0.dist-info/WHEEL
vitu-2.1.0.dist-info/top_level.txt
vitu-2.1.0.dist-info/RECORD
