Metadata-Version: 2.1
Name: vitu
Version: 2.1.0
Summary: VITU/Halo - backtest framework
Home-page: http://vitu.ai
Author: VituTech
Author-email: service@vitutech.com
License: UNKNOWN
Keywords: vitu halo backtest
Platform: UNKNOWN
Classifier: Development Status :: 5 - Production/Stable
Classifier: Intended Audience :: Developers
Classifier: Topic :: Software Development :: Build Tools
Classifier: Programming Language :: Python :: 3
Classifier: Programming Language :: Python :: 3.5
Classifier: Programming Language :: Python :: 3.6
Classifier: Programming Language :: Python :: 3.7
Requires-Python: >=3.0, <4
Provides-Extra: dev
Requires-Dist: check-manifest ; extra == 'dev'
Provides-Extra: test
Requires-Dist: coverage ; extra == 'test'
